kisspack/__init__.py
kisspack/common.py
kisspack/exceptions.py
kisspack/seq_setup.py
kisspack/seq_teardown.py
kisspack/seq_test.py
kisspack/setup_proc.py
kisspack/setup_set_param.py
kisspack/teardown_clear_param.py
kisspack/teardown_global.py
kisspack/test_check_setup.py
kisspack/test_normal_a.py
kisspack/test_normal_b.py
kisspack/test_normal_c.py
kisspack/test_normal_d.py
kisspack/test_proc_a.py
kisspack/test_proc_b.py
kisspack/test_proc_c.py
kisspack/test_proc_d.py
kisspack/test_thread_a.py
kisspack/test_thread_b.py
kisspack/test_thread_c.py
kisspack/test_thread_d.py
kisspack/params/common_task_params.yaml
kisspack/params/global_params.yaml
kisspack-1.0.0a2.dist-info/METADATA
kisspack-1.0.0a2.dist-info/RECORD
kisspack-1.0.0a2.dist-info/WHEEL
kisspack-1.0.0a2.dist-info/top_level.txt
