Metadata-Version: 2.1
Name: kisspack
Version: 1.0.0a2
Summary: A test package for KissATS
Home-page: UNKNOWN
Author: Bob Folkes
Author-email: bob@nwcompnet.com
License: UNKNOWN
Keywords: ats simple test automation
Platform: UNKNOWN
Classifier: Development Status :: 2 - Pre-Alpha
Classifier: Intended Audience :: Developers
Classifier: Intended Audience :: Information Technology
Classifier: Intended Audience :: Manufacturing
Classifier: Intended Audience :: Science/Research
Classifier: Topic :: Software Development :: Testing
Classifier: Topic :: Software Development :: Quality Assurance
Classifier: Topic :: Utilities
Classifier: License :: OSI Approved :: GNU General Public License v3 (GPLv3)
Classifier: Natural Language :: English
Classifier: Programming Language :: Python :: 2 :: Only
Classifier: Programming Language :: Python :: 2.7
Requires-Dist: kissats
Requires-Dist: pathlib2
